ctypes_ejdb-0.4.7.dist-info/DESCRIPTION.rst
ctypes_ejdb-0.4.7.dist-info/METADATA
ctypes_ejdb-0.4.7.dist-info/RECORD
ctypes_ejdb-0.4.7.dist-info/WHEEL
ctypes_ejdb-0.4.7.dist-info/entry_points.txt
ctypes_ejdb-0.4.7.dist-info/metadata.json
ctypes_ejdb-0.4.7.dist-info/top_level.txt
ejdb/__init__.py
ejdb/api.py
ejdb/bson.py
ejdb/c.py
ejdb/tc.py
ejdb/utils.py
ejdb/cmd/__init__.py
ejdb/cmd/run.py
ejdb/cmd/stub.py
