Metadata-Version: 2.0
Name: ctypes-ejdb
Version: 0.4.7
Summary: Python binding for EJDB built on ctypes.
Home-page: https://github.com/uranusjr/ctypes-ejdb
Author: Tzu-ping Chung
Author-email: uranusjr@gmail.com
License: BSD
Keywords: ctypes-ejdb
Platform: UNKNOWN
Classifier: Development Status :: 2 - Pre-Alpha
Classifier: Intended Audience :: Developers
Classifier: License :: OSI Approved :: BSD License
Classifier: Natural Language :: English
Classifier: Programming Language :: Python :: 2
Classifier: Programming Language :: Python :: 2.7
Classifier: Programming Language :: Python :: 3
Classifier: Programming Language :: Python :: 3.3
Classifier: Programming Language :: Python :: 3.4
Classifier: Programming Language :: Python :: 3.5
Requires-Dist: six
Provides-Extra: cli
Requires-Dist: click; extra == 'cli'
Requires-Dist: ptpython; extra == 'cli'
Requires-Dist: pystandardpaths; extra == 'cli'
